nxpy_past-1.0.3-py3.10-nspkg.pth
nxpy/core/past/__init__.py
nxpy/core/past/past.py
nxpy_past-1.0.3.dist-info/LICENSE.txt
nxpy_past-1.0.3.dist-info/METADATA
nxpy_past-1.0.3.dist-info/WHEEL
nxpy_past-1.0.3.dist-info/namespace_packages.txt
nxpy_past-1.0.3.dist-info/top_level.txt
nxpy_past-1.0.3.dist-info/RECORD
