Metadata-Version: 2.1
Name: nxpy-past
Version: 1.0.3
Summary: Python version based conditionals
Home-page: https://github.com/nmusatti/nxpy
Author: Nicola Musatti
Author-email: nicola.musatti@gmail.com
License: Boost Software License 1.0 (BSL-1.0)
Project-URL: Documentation, https://nxpy.readthedocs.io/en/latest/past.html
Project-URL: Source Code, https://github.com/nmusatti/nxpy/tree/master/libs/past
Platform: UNKNOWN
Classifier: Development Status :: 5 - Production/Stable
Classifier: Intended Audience :: Developers
Classifier: License :: OSI Approved :: Boost Software License 1.0 (BSL-1.0)
Classifier: Programming Language :: Python :: 2
Classifier: Programming Language :: Python :: 2.7
Classifier: Programming Language :: Python :: 3
Classifier: Programming Language :: Python :: 3.6
Classifier: Programming Language :: Python :: 3.7
Classifier: Programming Language :: Python :: 3.8
Classifier: Programming Language :: Python :: 3.9
Classifier: Topic :: Software Development :: Libraries
License-File: LICENSE.txt
